zunis/__init__.py
zunis/integration/__init__.py
zunis/integration/adaptive_survey_integrator.py
zunis/integration/base_integrator.py
zunis/integration/default_integrator.py
zunis/integration/dkltrainer_integrator.py
zunis/integration/fixed_sample_integrator.py
zunis/integration/flat_survey_integrator.py
zunis/integration/integratorAPI.py
zunis/models/__init__.py
zunis/models/generators.py
zunis/models/utils.py
zunis/models/flows/__init__.py
zunis/models/flows/general_flow.py
zunis/models/flows/masking.py
zunis/models/flows/sampling.py
zunis/models/flows/analytic_flows/__init__.py
zunis/models/flows/analytic_flows/analytic_flow.py
zunis/models/flows/analytic_flows/element_wise.py
zunis/models/flows/backprop_jacobian_flows/__init__.py
zunis/models/flows/backprop_jacobian_flows/general_backprop_j_flow.py
zunis/models/flows/backprop_jacobian_flows/nnflows.py
zunis/models/flows/backprop_jacobian_flows/simple_backprop_flows.py
zunis/models/flows/coupling_cells/__init__.py
zunis/models/flows/coupling_cells/general_coupling.py
zunis/models/flows/coupling_cells/real_nvp.py
zunis/models/flows/coupling_cells/transforms.py
zunis/models/flows/coupling_cells/piecewise_coupling/__init__.py
zunis/models/flows/coupling_cells/piecewise_coupling/piecewise_linear.py
zunis/models/flows/coupling_cells/piecewise_coupling/piecewise_quadratic.py
zunis/models/flows/sequential/__init__.py
zunis/models/flows/sequential/invertible_sequential.py
zunis/models/flows/sequential/repeated_cell.py
zunis/models/layers/__init__.py
zunis/models/layers/activations.py
zunis/models/layers/trainable.py
zunis/training/__init__.py
zunis/training/weighted_dataset/__init__.py
zunis/training/weighted_dataset/dkl_training.py
zunis/training/weighted_dataset/generators.py
zunis/training/weighted_dataset/stateful_trainer.py
zunis/training/weighted_dataset/training_record.py
zunis/training/weighted_dataset/variance_training.py
zunis/training/weighted_dataset/weighted_dataset_trainer.py
zunis/utils/__init__.py
zunis-0.3.dist-info/LICENSE
zunis-0.3.dist-info/METADATA
zunis-0.3.dist-info/WHEEL
zunis-0.3.dist-info/top_level.txt
zunis-0.3.dist-info/RECORD
