Metadata-Version: 2.1
Name: zunis
Version: 0.3
Summary: Neural Importance Sampling
Home-page: https://zunis.readthedocs.io
Author: Nicolas Deutschmann
Author-email: nicolas.deutschmann@gmail.com
License: MIT
Download-URL: https://github.com/ndeutschmann/zunis
Platform: UNKNOWN
License-File: LICENSE
Requires-Dist: numpy (==1.19.1)
Requires-Dist: pandas (==1.1.0)
Requires-Dist: torch (==1.6.0)
Requires-Dist: abc-property (==1.0)
Requires-Dist: dictwrapper (==1.3)
Requires-Dist: ruamel.yaml (<=0.16.12)
